Class163_NexT/__init__.py
Class163_NexT/models/__init__.py
Class163_NexT/models/music.py
Class163_NexT/models/playlist.py
Class163_NexT/utils/__init__.py
Class163_NexT/utils/cookies_manager.py
Class163_NexT/utils/playwright_login.py
Class163_NexT/utils/save_run.py
Class163_NexT/utils/selenium_login.py
class163_next-0.3.17.dist-info/licenses/LICENSE
class163_next-0.3.17.dist-info/METADATA
class163_next-0.3.17.dist-info/WHEEL
class163_next-0.3.17.dist-info/top_level.txt
class163_next-0.3.17.dist-info/RECORD
