Metadata-Version: 2.4
Name: Class163_NexT
Version: 0.3.17
Summary: Download musics from the offical API of Netease Music.
Author-email: CooooldWind_ <3091868003@qq.com>
License: AGPL-3.0-or-later
Requires-Python: >=3.9
License-File: LICENSE
Requires-Dist: cryptography>=45.0.7
Requires-Dist: mutagen>=1.47.0
Requires-Dist: netease-encode-api>=1.2.3
Requires-Dist: playwright>=1.55.0
Requires-Dist: selenium>=4.35.0
Dynamic: license-file
